cn2num/__init__.py
cn2num-0.1.1.dist-info/LICENSE
cn2num-0.1.1.dist-info/METADATA
cn2num-0.1.1.dist-info/WHEEL
cn2num-0.1.1.dist-info/top_level.txt
cn2num-0.1.1.dist-info/RECORD
