Metadata-Version: 2.1
Name: cn2num
Version: 0.1.1
Summary: A Simple package transform Chinese numerals into Arabic numerals
Home-page: http://github.com/anhenghuang/cn2num
Author: anhenghuang
Author-email: contact@huanganheng.com
License: MIT
Platform: UNKNOWN
Classifier: Programming Language :: Python :: 3
Classifier: License :: OSI Approved :: MIT License
Classifier: Operating System :: OS Independent
